easywaves/__init__.py
easywaves/curves.py
easywaves/easywaves.py
easywaves-0.4.3.dist-info/METADATA
easywaves-0.4.3.dist-info/WHEEL
easywaves-0.4.3.dist-info/top_level.txt
easywaves-0.4.3.dist-info/RECORD
